[{"place_id": 75477635, "licence": "Data \u00a9 OpenStreetMap contributors, ODbL 1.0. https://osm.org/copyright", "osm_type": "node", "osm_id": 7147521855, "boundingbox": ["51.5384259", "51.5484259", "-0.0291533", "-0.0191533"], "lat": "51.5434259", "lon": "-0.0241533", "display_name": "Hackney Wick, White Post Lane, Fish Island, Bow, London Borough of Tower Hamlets, London, Greater London, England, E9 5ER, United Kingdom", "class": "railway", "type": "station", "importance": 0.5606852804421033, "icon": "https://nominatim.openstreetmap.org/ui/mapicons/transport_train_station2.p.20.png"}, {"place_id": 47023087, "licence": "Data \u00a9 OpenStreetMap contributors, ODbL 1.0. https://osm.org/copyright", "osm_type": "node", "osm_id": 3939373094, "boundingbox": ["51.524354", "51.564354", "-0.0454673", "-0.0054673"], "lat": "51.544354", "lon": "-0.0254673", "display_name": "Hackney Wick, London Borough of Hackney, London, Greater London, England, E9 5NN, United Kingdom", "class": "place", "type": "suburb", "importance": 0.5527582828459303, "icon": "https://nominatim.openstreetmap.org/ui/mapicons/poi_place_village.p.20.png"}, {"place_id": 641328, "licence": "Data \u00a9 OpenStreetMap contributors, ODbL 1.0. https://osm.org/copyright", "osm_type": "node", "osm_id": 250672885, "boundingbox": ["51.5426515", "51.5427515", "-0.0285159", "-0.0284159"], "lat": "51.5427015", "lon": "-0.0284659", "display_name": "Hackney Wick, East Cross Route, East Wick, Hackney Wick, London Borough of Hackney, London, Greater London, England, E9 5FU, United Kingdom", "class": "highway", "type": "motorway_junction", "importance": 0.2001}, {"place_id": 3654971, "licence": "Data \u00a9 OpenStreetMap contributors, ODbL 1.0. https://osm.org/copyright", "osm_type": "node", "osm_id": 469788974, "boundingbox": ["51.5467467", "51.5468467", "-0.0295329", "-0.0294329"], "lat": "51.5467967", "lon": "-0.0294829", "display_name": "Hackney Wick, Eastway, East Wick, Hackney Wick, London Borough of Hackney, London, Greater London, England, E9 5JE, United Kingdom", "class": "highway", "type": "bus_stop", "importance": 0.20000999999999997, "icon": "https://nominatim.openstreetmap.org/ui/mapicons/transport_bus_stop2.p.20.png"}, {"place_id": 15901765, "licence": "Data \u00a9 OpenStreetMap contributors, ODbL 1.0. https://osm.org/copyright", "osm_type": "node", "osm_id": 1735591561, "boundingbox": ["51.5433267", "51.5434267", "-0.0249729", "-0.0248729"], "lat": "51.5433767", "lon": "-0.0249229", "display_name": "Hackney Wick, White Post Lane, Fish Island, Bow, London Borough of Tower Hamlets, London, Greater London, England, E9 5ER, United Kingdom", "class": "railway", "type": "stop", "importance": 0.20000999999999997}, {"place_id": 23307937, "licence": "Data \u00a9 OpenStreetMap contributors, ODbL 1.0. https://osm.org/copyright", "osm_type": "node", "osm_id": 2535817621, "boundingbox": ["51.5434112", "51.5435112", "-0.0237458", "-0.0236458"], "lat": "51.5434612", "lon": "-0.0236958", "display_name": "Hackney Wick, Queens Yard, Bow, London Borough of Tower Hamlets, London, Greater London, England, E9 5EN, United Kingdom", "class": "railway", "type": "stop", "importance": 0.20000999999999997}]