[{"place_id": 14837597, "licence": "Data \u00a9 OpenStreetMap contributors, ODbL 1.0. https://osm.org/copyright", "osm_type": "node", "osm_id": 1569016949, "boundingbox": ["51.501882", "51.581882", "-0.2379358", "-0.1579358"], "lat": "51.541882", "lon": "-0.1979358", "display_name": "Kilburn, London, Greater London, England, NW6 4JL, United Kingdom", "class": "place", "type": "town", "importance": 0.5596118305042289, "icon": "https://nominatim.openstreetmap.org/ui/mapicons/poi_place_town.p.20.png"}, {"place_id": 69396850, "licence": "Data \u00a9 OpenStreetMap contributors, ODbL 1.0. https://osm.org/copyright", "osm_type": "node", "osm_id": 6436648511, "boundingbox": ["51.5419889", "51.5519889", "-0.2103385", "-0.2003385"], "lat": "51.5469889", "lon": "-0.2053385", "display_name": "Kilburn, Exeter Road, Brondesbury, London Borough of Brent, London, Greater London, England, NW2 3UH, United Kingdom", "class": "railway", "type": "station", "importance": 0.5343074308132381, "icon": "https://nominatim.openstreetmap.org/ui/mapicons/transport_train_station2.p.20.png"}, {"place_id": 297786394, "licence": "Data \u00a9 OpenStreetMap contributors, ODbL 1.0. https://osm.org/copyright", "osm_type": "relation", "osm_id": 946734, "boundingbox": ["53.0008589", "53.0213937", "-1.4615344", "-1.4208109"], "lat": "53.006552", "lon": "-1.4307009", "display_name": "Kilburn CP, Amber Valley, Derbyshire, England, United Kingdom", "class": "boundary", "type": "administrative", "importance": 0.45609057542022047, "icon": "https://nominatim.openstreetmap.org/ui/mapicons/poi_boundary_administrative.p.20.png"}, {"place_id": 52618372, "licence": "Data \u00a9 OpenStreetMap contributors, ODbL 1.0. https://osm.org/copyright", "osm_type": "node", "osm_id": 4597195926, "boundingbox": ["54.1891636", "54.2291636", "-1.2339246", "-1.1939246"], "lat": "54.2091636", "lon": "-1.2139246", "display_name": "Kilburn, North Yorkshire, England, YO61 4AH, United Kingdom", "class": "place", "type": "village", "importance": 0.4493067919005157, "icon": "https://nominatim.openstreetmap.org/ui/mapicons/poi_place_village.p.20.png"}, {"place_id": 298812827, "licence": "Data \u00a9 OpenStreetMap contributors, ODbL 1.0. https://osm.org/copyright", "osm_type": "relation", "osm_id": 7378257, "boundingbox": ["-34.8709364", "-34.848516", "138.5781909", "138.5928573"], "lat": "-34.8596902", "lon": "138.5855855", "display_name": "Kilburn, Adelaide, City of Port Adelaide Enfield, South Australia, 5084, Australia", "class": "boundary", "type": "administrative", "importance": 0.4090422669932742, "icon": "https://nominatim.openstreetmap.org/ui/mapicons/poi_boundary_administrative.p.20.png"}, {"place_id": 87987747, "licence": "Data \u00a9 OpenStreetMap contributors, ODbL 1.0. https://osm.org/copyright", "osm_type": "node", "osm_id": 8626110036, "boundingbox": ["53.01278", "53.01288", "-1.4390222", "-1.4389222"], "lat": "53.01283", "lon": "-1.4389722", "display_name": "Kilburn, Rawson Green, Kilburn CP, Openwoodgate, Amber Valley, Derbyshire, England, DE56 0LN, United Kingdom", "class": "railway", "type": "site", "importance": 0.3985709817044999}, {"place_id": 298427604, "licence": "Data \u00a9 OpenStreetMap contributors, ODbL 1.0. https://osm.org/copyright", "osm_type": "relation", "osm_id": 6190732, "boundingbox": ["52.1911516", "52.2167887", "-8.6212274", "-8.5979652"], "lat": "52.203962000000004", "lon": "-8.608479182137996", "display_name": "Kilburn, Caherduggan ED, The Municipal District of Kanturk \u2013 Mallow, County Cork, Munster, \u00c9ire / Ireland", "class": "boundary", "type": "administrative", "importance": 0.36, "icon": "https://nominatim.openstreetmap.org/ui/mapicons/poi_boundary_administrative.p.20.png"}, {"place_id": 299468103, "licence": "Data \u00a9 OpenStreetMap contributors, ODbL 1.0. https://osm.org/copyright", "osm_type": "relation", "osm_id": 6294235, "boundingbox": ["52.1410127", "52.1494011", "-9.7507082", "-9.7317396"], "lat": "52.1452147", "lon": "-9.742454379365602", "display_name": "Kilburn, Milltown ED, Kenmare Municipal District, County Kerry, Munster, \u00c9ire / Ireland", "class": "boundary", "type": "administrative", "importance": 0.36, "icon": "https://nominatim.openstreetmap.org/ui/mapicons/poi_boundary_administrative.p.20.png"}, {"place_id": 16230014, "licence": "Data \u00a9 OpenStreetMap contributors, ODbL 1.0. https://osm.org/copyright", "osm_type": "node", "osm_id": 1765087160, "boundingbox": ["-34.8645688", "-34.8545688", "138.5733734", "138.5833734"], "lat": "-34.8595688", "lon": "138.5783734", "display_name": "Kilburn, Railway Terrace, Kilburn, Adelaide, City of Port Adelaide Enfield, South Australia, 5084, Australia", "class": "railway", "type": "station", "importance": 0.34859140675544004, "icon": "https://nominatim.openstreetmap.org/ui/mapicons/transport_train_station2.p.20.png"}, {"place_id": 230409969, "licence": "Data \u00a9 OpenStreetMap contributors, ODbL 1.0. https://osm.org/copyright", "osm_type": "way", "osm_id": 610274255, "boundingbox": ["55.7743388", "55.7758589", "-4.4391417", "-4.436212"], "lat": "55.775072800000004", "lon": "-4.437497064359826", "display_name": "Kilburn, Neilston, East Renfrewshire, Alba / Scotland, G78 3BP, United Kingdom", "class": "landuse", "type": "farmyard", "importance": 0.3100099999999999}]