[{"place_id": 20369472, "licence": "Data \u00a9 OpenStreetMap contributors, ODbL 1.0. https://osm.org/copyright", "osm_type": "node", "osm_id": 2354980085, "boundingbox": ["51.5152181", "51.5153181", "-0.1420578", "-0.1419578"], "lat": "51.5152681", "lon": "-0.1420078", "display_name": "Oxford Circus, Oxford Street, East Marylebone, Mayfair, City of Westminster, Greater London, England, W1B 2ER, United Kingdom", "class": "tourism", "type": "information", "importance": 0.6857594484862148, "icon": "https://nominatim.openstreetmap.org/ui/mapicons/amenity_information.p.20.png"}, {"place_id": 60669951, "licence": "Data \u00a9 OpenStreetMap contributors, ODbL 1.0. https://osm.org/copyright", "osm_type": "node", "osm_id": 5614077964, "boundingbox": ["51.5101808", "51.5201808", "-0.1460118", "-0.1360118"], "lat": "51.5151808", "lon": "-0.1410118", "display_name": "Oxford Circus, Argyll Street, Soho, City of Westminster, Greater London, England, W1F 7TN, United Kingdom", "class": "railway", "type": "station", "importance": 0.6163024574626617, "icon": "https://nominatim.openstreetmap.org/ui/mapicons/transport_train_station2.p.20.png"}, {"place_id": 14827757, "licence": "Data \u00a9 OpenStreetMap contributors, ODbL 1.0. https://osm.org/copyright", "osm_type": "node", "osm_id": 1637478197, "boundingbox": ["51.5154117", "51.5155117", "-0.1408611", "-0.1407611"], "lat": "51.5154617", "lon": "-0.1408111", "display_name": "Oxford Circus, Oxford Street, East Marylebone, Mayfair, City of Westminster, Greater London, England, W1D 2LT, United Kingdom", "class": "railway", "type": "stop", "importance": 0.6163024574626617}, {"place_id": 375155, "licence": "Data \u00a9 OpenStreetMap contributors, ODbL 1.0. https://osm.org/copyright", "osm_type": "node", "osm_id": 248200076, "boundingbox": ["51.5156056", "51.5157056", "-0.1420667", "-0.1419667"], "lat": "51.5156556", "lon": "-0.1420167", "display_name": "Oxford Circus, Regent Street, East Marylebone, Mayfair, City of Westminster, Greater London, England, W1B 3AP, United Kingdom", "class": "railway", "type": "stop", "importance": 0.6163024574626617}, {"place_id": 15517325, "licence": "Data \u00a9 OpenStreetMap contributors, ODbL 1.0. https://osm.org/copyright", "osm_type": "node", "osm_id": 1742756469, "boundingbox": ["51.5156076", "51.5157076", "-0.1418187", "-0.1417187"], "lat": "51.5156576", "lon": "-0.1417687", "display_name": "Oxford Circus, Regent Street, East Marylebone, Mayfair, City of Westminster, Greater London, England, W1B 2ES, United Kingdom", "class": "railway", "type": "stop", "importance": 0.6163024574626617}, {"place_id": 150205828, "licence": "Data \u00a9 OpenStreetMap contributors, ODbL 1.0. https://osm.org/copyright", "osm_type": "way", "osm_id": 176578357, "boundingbox": ["-34.9898703", "-34.9898665", "138.5926437", "138.5928566"], "lat": "-34.9898703", "lon": "138.5926437", "display_name": "Oxford Circus, Colonel Light Gardens, Adelaide, City of Mitcham, South Australia, 5041, Australia", "class": "highway", "type": "residential", "importance": 0.30000999999999994}, {"place_id": 17692734, "licence": "Data \u00a9 OpenStreetMap contributors, ODbL 1.0. https://osm.org/copyright", "osm_type": "node", "osm_id": 2047806082, "boundingbox": ["51.5151792", "51.5152792", "-0.1421027", "-0.1420027"], "lat": "51.5152292", "lon": "-0.1420527", "display_name": "Oxford Circus, Oxford Street, East Marylebone, Mayfair, City of Westminster, Greater London, England, W1B 2ER, United Kingdom", "class": "junction", "type": "crossroads", "importance": 0.20000999999999997}, {"place_id": 308745856, "licence": "Data \u00a9 OpenStreetMap contributors, ODbL 1.0. https://osm.org/copyright", "osm_type": "node", "osm_id": 107333, "boundingbox": ["51.5152555", "51.5153555", "-0.142016", "-0.141916"], "lat": "51.5153055", "lon": "-0.141966", "display_name": "Oxford Circus, Regent Street, East Marylebone, Mayfair, City of Westminster, Greater London, England, W1B 3AH, United Kingdom", "class": "junction", "type": "crossroads", "importance": 0.20000999999999997}, {"place_id": 309651230, "licence": "Data \u00a9 OpenStreetMap contributors, ODbL 1.0. https://osm.org/copyright", "osm_type": "node", "osm_id": 25496587, "boundingbox": ["51.5152438", "51.5153438", "-0.1421215", "-0.1420215"], "lat": "51.5152938", "lon": "-0.1420715", "display_name": "Oxford Circus, Regent Street, East Marylebone, Mayfair, City of Westminster, Greater London, England, W1B 2ER, United Kingdom", "class": "junction", "type": "crossroads", "importance": 0.20000999999999997}, {"place_id": 15587403, "licence": "Data \u00a9 OpenStreetMap contributors, ODbL 1.0. https://osm.org/copyright", "osm_type": "node", "osm_id": 1742756486, "boundingbox": ["51.515575", "51.515675", "-0.1423317", "-0.1422317"], "lat": "51.515625", "lon": "-0.1422817", "display_name": "Oxford Circus, Regent Street, East Marylebone, Mayfair, City of Westminster, Greater London, England, W1B 2HB, United Kingdom", "class": "railway", "type": "stop", "importance": 0.20000999999999997}]