[{"place_id": 59009237, "licence": "Data \u00a9 OpenStreetMap contributors, ODbL 1.0. https://osm.org/copyright", "osm_type": "node", "osm_id": 5495828135, "boundingbox": ["51.5214341", "51.5314341", "-0.2889348", "-0.2789348"], "lat": "51.5264341", "lon": "-0.2839348", "display_name": "Park Royal, Masons Green Lane, Park Royal, London Borough of Ealing, London, Greater London, England, W3 0LT, United Kingdom", "class": "railway", "type": "station", "importance": 0.6225802033167898, "icon": "https://nominatim.openstreetmap.org/ui/mapicons/transport_train_station2.p.20.png"}, {"place_id": 78132340, "licence": "Data \u00a9 OpenStreetMap contributors, ODbL 1.0. https://osm.org/copyright", "osm_type": "node", "osm_id": 7626551300, "boundingbox": ["51.5084366", "51.5484366", "-0.2997183", "-0.2597183"], "lat": "51.5284366", "lon": "-0.2797183", "display_name": "Park Royal, London Borough of Ealing, London, Greater London, England, NW10 7QH, United Kingdom", "class": "place", "type": "suburb", "importance": 0.5634557423311779, "icon": "https://nominatim.openstreetmap.org/ui/mapicons/poi_place_village.p.20.png"}, {"place_id": 96244849, "licence": "Data \u00a9 OpenStreetMap contributors, ODbL 1.0. https://osm.org/copyright", "osm_type": "node", "osm_id": 9476691151, "boundingbox": ["51.5271231", "51.5272231", "-0.2768578", "-0.2767578"], "lat": "51.5271731", "lon": "-0.2768078", "display_name": "Park Royal, Johnsons Way, Park Royal, London Borough of Ealing, London, Greater London, England, NW10 7PF, United Kingdom", "class": "railway", "type": "site", "importance": 0.5027787078968705}, {"place_id": 7257251, "licence": "Data \u00a9 OpenStreetMap contributors, ODbL 1.0. https://osm.org/copyright", "osm_type": "node", "osm_id": 918817930, "boundingbox": ["49.3067032", "49.3467032", "-123.1587237", "-123.1187237"], "lat": "49.3267032", "lon": "-123.1387237", "display_name": "Park Royal, West Vancouver, Metro Vancouver Regional District, British Columbia, V7T 1A0, Canada", "class": "place", "type": "suburb", "importance": 0.47501, "icon": "https://nominatim.openstreetmap.org/ui/mapicons/poi_place_village.p.20.png"}, {"place_id": 191677795, "licence": "Data \u00a9 OpenStreetMap contributors, ODbL 1.0. https://osm.org/copyright", "osm_type": "way", "osm_id": 347367363, "boundingbox": ["49.6716712", "49.6735539", "-112.8242129", "-112.817768"], "lat": "49.672581699999995", "lon": "-112.82067280000001", "display_name": "Park Royal, Lethbridge, Alberta, Canada", "class": "landuse", "type": "residential", "importance": 0.4000099999999999}, {"place_id": 241600652, "licence": "Data \u00a9 OpenStreetMap contributors, ODbL 1.0. https://osm.org/copyright", "osm_type": "way", "osm_id": 665563734, "boundingbox": ["41.1799348", "41.180585", "28.8872909", "28.8881522"], "lat": "41.18026285", "lon": "28.887710848887938", "display_name": "Park Royal, G\u00f6kt\u00fcrk Merkez Mahallesi, Ey\u00fcpsultan, \u0130stanbul, Marmara B\u00f6lgesi, T\u00fcrkiye", "class": "landuse", "type": "residential", "importance": 0.4000099999999999}, {"place_id": 245782239, "licence": "Data \u00a9 OpenStreetMap contributors, ODbL 1.0. https://osm.org/copyright", "osm_type": "way", "osm_id": 685278071, "boundingbox": ["40.8881267", "40.8887902", "29.2663898", "29.2680232"], "lat": "40.8884993", "lon": "29.267218520536257", "display_name": "Park Royal, Fevzi \u00c7akmak Mahallesi, Pendik, \u0130stanbul, Marmara B\u00f6lgesi, 34899, T\u00fcrkiye", "class": "landuse", "type": "residential", "importance": 0.4000099999999999}, {"place_id": 363094149, "licence": "Data \u00a9 OpenStreetMap contributors, ODbL 1.0. https://osm.org/copyright", "osm_type": "way", "osm_id": 1179633425, "boundingbox": ["41.0272486", "41.028688", "-80.7615862", "-80.760624"], "lat": "41.02799965", "lon": "-80.76110242521085", "display_name": "Park Royal, Canfield, Mahoning County, Ohio, United States", "class": "landuse", "type": "residential", "importance": 0.4000099999999999}, {"place_id": 272230711, "licence": "Data \u00a9 OpenStreetMap contributors, ODbL 1.0. https://osm.org/copyright", "osm_type": "way", "osm_id": 844107528, "boundingbox": ["38.4735507", "38.4784011", "-90.3829073", "-90.3773015"], "lat": "38.476043000000004", "lon": "-90.38112865684067", "display_name": "Park Royal, Missouri, United States", "class": "landuse", "type": "residential", "importance": 0.4000099999999999}, {"place_id": 242613409, "licence": "Data \u00a9 OpenStreetMap contributors, ODbL 1.0. https://osm.org/copyright", "osm_type": "way", "osm_id": 670795525, "boundingbox": ["38.7849905", "38.7864062", "-75.3100464", "-75.3084505"], "lat": "38.785698350000004", "lon": "-75.30925233469776", "display_name": "Park Royal, Milton, Sussex County, Delaware, United States", "class": "landuse", "type": "residential", "importance": 0.4000099999999999}]