[{"place_id": 3648769, "licence": "Data \u00a9 OpenStreetMap contributors, ODbL 1.0. https://osm.org/copyright", "osm_type": "node", "osm_id": 469760990, "boundingbox": ["51.5586297", "51.5686297", "-0.2850532", "-0.2750532"], "lat": "51.5636297", "lon": "-0.2800532", "display_name": "Wembley Park, Bridge Road, London Borough of Brent, London, Greater London, England, HA9 9AA, United Kingdom", "class": "railway", "type": "station", "importance": 0.6410042425468967, "icon": "https://nominatim.openstreetmap.org/ui/mapicons/transport_train_station2.p.20.png"}, {"place_id": 298459768, "licence": "Data \u00a9 OpenStreetMap contributors, ODbL 1.0. https://osm.org/copyright", "osm_type": "relation", "osm_id": 3808860, "boundingbox": ["51.5629602", "51.5639958", "-0.2806291", "-0.2790285"], "lat": "51.56347855", "lon": "-0.27969830907470106", "display_name": "Wembley Park, Bridge Road, London Borough of Brent, London, Greater London, England, HA9 9AA, United Kingdom", "class": "building", "type": "train_station", "importance": 0.6410042425468967}, {"place_id": 195540203, "licence": "Data \u00a9 OpenStreetMap contributors, ODbL 1.0. https://osm.org/copyright", "osm_type": "way", "osm_id": 384910553, "boundingbox": ["-10.9409114", "-10.940228", "-37.0579701", "-37.0573383"], "lat": "-10.9404741", "lon": "-37.05755441381026", "display_name": "Wembley Park, Jardins, Aracaju, Regi\u00e3o Geogr\u00e1fica Imediata de Aracaju, Regi\u00e3o Geogr\u00e1fica Intermedi\u00e1ria de Aracaju, Sergipe, Regi\u00e3o Nordeste, Brasil", "class": "landuse", "type": "residential", "importance": 0.4000099999999999}, {"place_id": 209377004, "licence": "Data \u00a9 OpenStreetMap contributors, ODbL 1.0. https://osm.org/copyright", "osm_type": "way", "osm_id": 461983881, "boundingbox": ["47.4308001", "47.4338883", "-122.1066514", "-122.1013211"], "lat": "47.43268195", "lon": "-122.10359280093532", "display_name": "Wembley Park, King County, Washington, United States", "class": "landuse", "type": "residential", "importance": 0.4000099999999999}, {"place_id": 109693919, "licence": "Data \u00a9 OpenStreetMap contributors, ODbL 1.0. https://osm.org/copyright", "osm_type": "way", "osm_id": 23000329, "boundingbox": ["-27.4961514", "-27.4946761", "153.0655669", "153.0667788"], "lat": "-27.4956642", "lon": "153.06633983699555", "display_name": "Wembley Park, Camp Hill, Brisbane City, Queensland, Australia", "class": "landuse", "type": "residential", "importance": 0.39999999999999997}, {"place_id": 168753512, "licence": "Data \u00a9 OpenStreetMap contributors, ODbL 1.0. https://osm.org/copyright", "osm_type": "way", "osm_id": 254311512, "boundingbox": ["-39.9110376", "-39.9058456", "175.0662727", "175.0721422"], "lat": "-39.9077543", "lon": "175.07033067216304", "display_name": "Wembley Park, Aramoho, Whanganui, Whanganui District, Manawat\u016b-Whanganui, New Zealand/Aotearoa", "class": "landuse", "type": "recreation_ground", "importance": 0.39999999999999997}, {"place_id": 108434146, "licence": "Data \u00a9 OpenStreetMap contributors, ODbL 1.0. https://osm.org/copyright", "osm_type": "way", "osm_id": 20398557, "boundingbox": ["-27.4917558", "-27.4877171", "153.0564632", "153.0645154"], "lat": "-27.48973315", "lon": "153.06315622652977", "display_name": "Wembley Park, Coorparoo, Brisbane City, Queensland, Australia", "class": "leisure", "type": "park", "importance": 0.35000000000000003}, {"place_id": 130244283, "licence": "Data \u00a9 OpenStreetMap contributors, ODbL 1.0. https://osm.org/copyright", "osm_type": "way", "osm_id": 110009467, "boundingbox": ["36.2749921", "36.2770996", "-94.2190449", "-94.2187086"], "lat": "36.275932", "lon": "-94.2190449", "display_name": "Wembley Park, Cave Springs, Benton County, Arkansas, 72718, United States", "class": "highway", "type": "residential", "importance": 0.3}, {"place_id": 34936927, "licence": "Data \u00a9 OpenStreetMap contributors, ODbL 1.0. https://osm.org/copyright", "osm_type": "node", "osm_id": 2907810120, "boundingbox": ["51.5634953", "51.5635953", "-0.2792689", "-0.2791689"], "lat": "51.5635453", "lon": "-0.2792189", "display_name": "Wembley Park, Bridge Road, London Borough of Brent, London, Greater London, England, HA9 9AH, United Kingdom", "class": "railway", "type": "stop", "importance": 0.2001}, {"place_id": 34951960, "licence": "Data \u00a9 OpenStreetMap contributors, ODbL 1.0. https://osm.org/copyright", "osm_type": "node", "osm_id": 2907810196, "boundingbox": ["51.5638218", "51.5639218", "-0.2810713", "-0.2809713"], "lat": "51.5638718", "lon": "-0.2810213", "display_name": "Wembley Park, Brook Avenue, Preston, London Borough of Brent, London, Greater London, England, HA9 8PG, United Kingdom", "class": "railway", "type": "stop", "importance": 0.2001}]